sdn_manager-1.0.3.dist-info/METADATA
sdn_manager-1.0.3.dist-info/WHEEL
sdn_manager-1.0.3.dist-info/top_level.txt
sdn_manager-1.0.3.dist-info/DESCRIPTION.rst
sdn_manager-1.0.3.dist-info/RECORD
sdn_manager-1.0.3.dist-info/metadata.json
sdn_manager-1.0.3.data/scripts/sdn-manager
eu/__init__.py
eu/softfire/__init__.py
eu/softfire/sdn/__init__.py
eu/softfire/sdn/exm_cli.py
eu/softfire/sdn/main/__init__.py
eu/softfire/sdn/main/SdnManager.py
eu/softfire/sdn/utils/__init__.py
eu/softfire/sdn/utils/static_config.py
eu/softfire/sdn/utils/utils.py
eu/softfire/sdn/utils/exceptions.py
