Metadata-Version: 2.0
Name: sdn-manager
Version: 1.0.3
Summary: The SoftFIRE SDN Manager
Home-page: http://softfire.eu/
Author: SoftFIRE
Author-email: softfire@softfire.eu
License: Apache 2
Keywords: python vnfm nfvo open baton openbaton sdk experiment manager softfire tosca openstack rest
Platform: UNKNOWN
Classifier: Development Status :: 4 - Beta
Classifier: Intended Audience :: Developers
Classifier: License :: OSI Approved :: Apache Software License
Requires-Dist: softfire-sdk (==1.1.4)
Requires-Dist: PyYAML
Requires-Dist: requests
